setup.py
ore/__init__.py
ore.recipe.fs.egg-info/PKG-INFO
ore.recipe.fs.egg-info/SOURCES.txt
ore.recipe.fs.egg-info/dependency_links.txt
ore.recipe.fs.egg-info/entry_points.txt
ore.recipe.fs.egg-info/namespace_packages.txt
ore.recipe.fs.egg-info/requires.txt
ore.recipe.fs.egg-info/top_level.txt
ore.recipe.fs.egg-info/zip-safe
ore/recipe/__init__.py
ore/recipe/fs/__init__.py