Metadata-Version: 1.0
Name: ore.recipe.fs
Version: 0.3.1
Summary: File and Directory Creation for Buildout, Extracted from lovely.recipe for minimal dependencies
Home-page: http://www.python.org/pypi/ore.recipe.fs
Author: Kapil Thangavelu
Author-email: kapil.foss@gmail.com
License: ZPL 2.1
Keywords: buildout recipe filesystem
Platform: UNKNOWN
